{
 "absolute_value": 0,
 "align_labels_right": 0,
 "creation": "2021-12-23 17:12:26.217074",
 "custom_format": 0,
 "default_print_language": "en",
 "disabled": 0,
 "doc_type": "Council Application",
 "docstatus": 0,
 "doctype": "Print Format",
 "font": "Default",
 "format_data": "[{\"fieldname\": \"print_heading_template\", \"fieldtype\": \"Custom HTML\", \"options\": \"<div class=\\\"print-heading\\\">\\t\\t\\t\\t<h2><div>Council Application</div><br><small class=\\\"sub-heading\\\">{{ doc.name }}</small>\\t\\t\\t\\t</h2></div>\"}, {\"fieldtype\": \"Section Break\", \"label\": \"Personal Information\"}, {\"fieldtype\": \"Column Break\"}, {\"fieldname\": \"applicant_name\", \"print_hide\": 0, \"label\": \"Full Name of the Applicant\"}, {\"fieldname\": \"email\", \"print_hide\": 0, \"label\": \"Email Id of the Applicant\"}, {\"fieldname\": \"contact\", \"print_hide\": 0, \"label\": \"Contact Number\"}, {\"fieldname\": \"dob\", \"print_hide\": 0, \"label\": \"Date of Birth\"}, {\"fieldtype\": \"Column Break\"}, {\"fieldname\": \"gender\", \"print_hide\": 0, \"label\": \"Gender\"}, {\"fieldname\": \"status_ri\", \"print_hide\": 0, \"label\": \"Status for the RI year 2022-23\"}, {\"fieldname\": \"formal_pic\", \"print_hide\": 0, \"label\": \"Upload a Straight Formal Picture\"}, {\"fieldname\": \"resume\", \"print_hide\": 0, \"label\": \"Updated Resume\"}, {\"fieldtype\": \"Section Break\", \"label\": \"Rotaract Information\"}, {\"fieldtype\": \"Column Break\"}, {\"fieldname\": \"home_club\", \"print_hide\": 0, \"label\": \"Home Club of the Applicant for the year 21-22(Current Year's Rotaract Club)\"}, {\"fieldname\": \"zone\", \"print_hide\": 0, \"label\": \"Zone\"}, {\"fieldname\": \"number_of_rotaractyears\", \"print_hide\": 0, \"label\": \"Total number of years in Rotaract\"}, {\"fieldname\": \"earlier_home_club\", \"print_hide\": 0, \"label\": \"Earlier Home Club\"}, {\"fieldname\": \"club_ri_21_22\", \"print_hide\": 0, \"label\": \"Your Club for the RI Year 2021-22(Applicable for Club Change)\"}, {\"fieldname\": \"strengths\", \"print_hide\": 0, \"label\": \"My Strengths\"}, {\"fieldname\": \"weakness\", \"print_hide\": 0, \"label\": \"My Weaknesses\"}, {\"fieldtype\": \"Column Break\"}, {\"fieldname\": \"experience_club\", \"print_hide\": 0, \"label\": \"Rotaract Experience at Club Level\"}, {\"fieldname\": \"experience_district\", \"print_hide\": 0, \"label\": \"Rotaract Experience at District Level\"}, {\"fieldname\": \"highlights\", \"print_hide\": 0, \"label\": \"Top 5 Highlights of your Rotaract Career\"}, {\"fieldtype\": \"Section Break\", \"label\": \"Application Preference\"}, {\"fieldtype\": \"Column Break\"}, {\"fieldname\": \"avenue_preference1\", \"print_hide\": 0, \"label\": \"Avenue Preference 1\"}, {\"fieldname\": \"designation1\", \"print_hide\": 0, \"label\": \"Which Designation are you applying for\"}, {\"fieldname\": \"reason1\", \"print_hide\": 0, \"label\": \"Reason for Preference 1\"}, {\"fieldname\": \"unique_avenue1\", \"print_hide\": 0, \"label\": \"Suggest one UNIQUE initiative that you will take in this avenue-1\"}, {\"fieldtype\": \"Column Break\"}, {\"fieldname\": \"avenue_preference2\", \"print_hide\": 0, \"label\": \"Avenue Preference 2\"}, {\"fieldname\": \"designation2\", \"print_hide\": 0, \"label\": \"Which Designation are you applying for\"}, {\"fieldname\": \"reason2\", \"print_hide\": 0, \"label\": \"Reason for Preference 2\"}, {\"fieldname\": \"unique_avenue2\", \"print_hide\": 0, \"label\": \"Suggest one UNIQUE initiative that you will take in this avenue-2\"}, {\"fieldtype\": \"Section Break\", \"label\": \"Tell us 2 Projects you wish to be a chairperson for?\"}, {\"fieldtype\": \"Column Break\"}, {\"fieldname\": \"project_select1\", \"print_hide\": 0, \"label\": \"Project 1\"}, {\"fieldtype\": \"Column Break\"}, {\"fieldname\": \"project_select2\", \"print_hide\": 0, \"label\": \"Project 2\"}, {\"fieldtype\": \"Section Break\", \"label\": \"\"}, {\"fieldtype\": \"Column Break\"}, {\"fieldname\": \"inspire_refer\", \"print_hide\": 0, \"label\": \"Who inspired/referred you to apply for the District Council 2022-23\"}, {\"fieldtype\": \"Section Break\", \"label\": \"Leadership\"}, {\"fieldtype\": \"Column Break\"}, {\"fieldname\": \"define_rotaract\", \"print_hide\": 0, \"label\": \"Define Rotaract in the most efficient way\"}, {\"fieldname\": \"expectation\", \"print_hide\": 0, \"label\": \"What do you expect to experience from this opportunity?\"}, {\"fieldtype\": \"Column Break\"}, {\"fieldname\": \"motivation\", \"print_hide\": 0, \"label\": \"What motivates you to be a part of the council?\"}, {\"fieldtype\": \"Section Break\", \"label\": \"No-Objection Certificate from Club\"}, {\"fieldtype\": \"Column Break\"}, {\"fieldname\": \"noc\", \"print_hide\": 0, \"label\": \"No Objection Certificate\"}, {\"fieldname\": \"president_name\", \"print_hide\": 0, \"label\": \"Name of the President\"}, {\"fieldname\": \"president_designation\", \"print_hide\": 0, \"label\": \"Designation\"}, {\"fieldname\": \"cetify\", \"print_hide\": 0, \"label\": \"I certify that the information shared above is true to my knowledge\"}, {\"fieldname\": \"date_submission\", \"print_hide\": 0, \"label\": \"Date of Submission\"}]",
 "idx": 0,
 "line_breaks": 1,
 "modified": "2021-12-23 17:13:40.970203",
 "modified_by": "Administrator",
 "module": "Pranali Reloaded",
 "name": "Council Application",
 "owner": "Administrator",
 "print_format_builder": 0,
 "print_format_type": "Jinja",
 "raw_printing": 0,
 "show_section_headings": 1,
 "standard": "Yes"
}